easyqr/__init__.py
easyqr/easyqr.py
easyqr-1.0.dist-info/LICENSE
easyqr-1.0.dist-info/METADATA
easyqr-1.0.dist-info/WHEEL
easyqr-1.0.dist-info/top_level.txt
easyqr-1.0.dist-info/RECORD
