Metadata-Version: 2.1
Name: easyqr
Version: 1.0
Summary: QR code conversion tool
Home-page: https://gitee.com/Rt_hum/Easyqr
Author: Mr.right
Author-email: 1003582810@qq.com
License: UNKNOWN
Platform: UNKNOWN
Classifier: Programming Language :: Python :: 3
Classifier: License :: OSI Approved :: MIT License
Classifier: Operating System :: OS Independent
Requires-Python: >=3.6
Requires-Dist: lxml
Requires-Dist: requests
Requires-Dist: requests-toolbelt
